ovos_skill_parrot/LICENSE
ovos_skill_parrot/MANIFEST.in
ovos_skill_parrot/README.md
ovos_skill_parrot/__init__.py
ovos_skill_parrot/requirements.txt
ovos_skill_parrot/version.py
ovos_skill_parrot/gui/qt5/nature.jpg
ovos_skill_parrot/gui/qt5/parrot.html
ovos_skill_parrot/gui/qt5/parrot.qml
ovos_skill_parrot/locale/ca-es/ParrotKeyword.voc
ovos_skill_parrot/locale/ca-es/StopKeyword.voc
ovos_skill_parrot/locale/ca-es/did.hear.dialog
ovos_skill_parrot/locale/ca-es/did.not.hear.dialog
ovos_skill_parrot/locale/ca-es/did.you.hear.me.intent
ovos_skill_parrot/locale/ca-es/not_parroting.dialog
ovos_skill_parrot/locale/ca-es/nothing.dialog
ovos_skill_parrot/locale/ca-es/parrot_start.dialog
ovos_skill_parrot/locale/ca-es/parrot_stop.dialog
ovos_skill_parrot/locale/ca-es/please.repeat.dialog
ovos_skill_parrot/locale/ca-es/repeat.stt.dialog
ovos_skill_parrot/locale/ca-es/repeat.stt.intent
ovos_skill_parrot/locale/ca-es/repeat.stt.old.dialog
ovos_skill_parrot/locale/ca-es/repeat.tts.dialog
ovos_skill_parrot/locale/ca-es/repeat.tts.intent
ovos_skill_parrot/locale/ca-es/skill.json
ovos_skill_parrot/locale/ca-es/speak.intent
ovos_skill_parrot/locale/ca-es/start_parrot.intent
ovos_skill_parrot/locale/ca-es/stop_parrot.intent
ovos_skill_parrot/locale/da-dk/ParrotKeyword.voc
ovos_skill_parrot/locale/da-dk/StopKeyword.voc
ovos_skill_parrot/locale/da-dk/did.hear.dialog
ovos_skill_parrot/locale/da-dk/did.not.hear.dialog
ovos_skill_parrot/locale/da-dk/did.you.hear.me.intent
ovos_skill_parrot/locale/da-dk/not_parroting.dialog
ovos_skill_parrot/locale/da-dk/nothing.dialog
ovos_skill_parrot/locale/da-dk/parrot_start.dialog
ovos_skill_parrot/locale/da-dk/parrot_stop.dialog
ovos_skill_parrot/locale/da-dk/please.repeat.dialog
ovos_skill_parrot/locale/da-dk/repeat.stt.dialog
ovos_skill_parrot/locale/da-dk/repeat.stt.intent
ovos_skill_parrot/locale/da-dk/repeat.stt.old.dialog
ovos_skill_parrot/locale/da-dk/repeat.tts.dialog
ovos_skill_parrot/locale/da-dk/repeat.tts.intent
ovos_skill_parrot/ovos_skill_parrot.egg-info/PKG-INFO
ovos_skill_parrot/ovos_skill_parrot.egg-info/SOURCES.txt
ovos_skill_parrot/ovos_skill_parrot.egg-info/dependency_links.txt
ovos_skill_parrot/ovos_skill_parrot.egg-info/entry_points.txt
ovos_skill_parrot/ovos_skill_parrot.egg-info/requires.txt
ovos_skill_parrot/ovos_skill_parrot.egg-info/top_level.txt
ovos_skill_parrot-0.1.25.dist-info/LICENSE
ovos_skill_parrot-0.1.25.dist-info/METADATA
ovos_skill_parrot-0.1.25.dist-info/WHEEL
ovos_skill_parrot-0.1.25.dist-info/entry_points.txt
ovos_skill_parrot-0.1.25.dist-info/top_level.txt
ovos_skill_parrot-0.1.25.dist-info/RECORD
