Metadata-Version: 2.1
Name: ovos-skill-parrot
Version: 0.1.25
Summary: Repeats what the user says
Home-page: https://github.com/OpenVoiceOS/ovos-skill-parrot
Author: OpenVoiceOS
Author-email: jarbasai@mailfence.com
License: Apache-2.0
Keywords: ovos skill plugin
License-File: LICENSE
Requires-Dist: ovos-workshop<8.0.0,>=7.0.0
